sagpy/__init__.py
sagpy/drawio_diagram.py
sagpy/generate_jobs.py
sagpy/sag_template.py
sagpy/sagpy.py
sagpy/utils.py
sagpy/sag_algorithms/__init__.py
sagpy/sag_algorithms/ecrts2019.py
sagpy/sag_algorithms/ros.py
sagpy-0.0.13.dist-info/METADATA
sagpy-0.0.13.dist-info/WHEEL
sagpy-0.0.13.dist-info/entry_points.txt
sagpy-0.0.13.dist-info/licenses/LICENSE
sagpy-0.0.13.dist-info/RECORD
