Metadata-Version: 2.3
Name: sagpy
Version: 0.0.13
Summary: Implementation of the Schedule-Abstraction Graph (SAG) in Python.
Project-URL: Homepage, https://github.com/RaduLucianR/sag-py
Project-URL: Issues, https://github.com/RaduLucianR/sag-py/issues
Author-email: Radu Lucian Radulescu <radlucradulescu@gmail.com>
Classifier: License :: OSI Approved :: BSD License
Classifier: Operating System :: Unix
Classifier: Programming Language :: Python :: 3
Requires-Python: >=3.12
Requires-Dist: drawpyo>=0.2.1
Requires-Dist: matplotlib>=3.6.3
Requires-Dist: networkx>=3.4.2
Requires-Dist: tqdm>=4.66.6
